CHANGES.rst
CHANGES_RECENT.rst
LICENSE.txt
MANIFEST.in
README.rst
TODO.rst
requirements.txt
setup.py
pypdfocr/__init__.py
pypdfocr/pypdfocr.py
pypdfocr/pypdfocr_filer.py
pypdfocr/pypdfocr_filer_dirs.py
pypdfocr/pypdfocr_filer_evernote.py
pypdfocr/pypdfocr_gs.py
pypdfocr/pypdfocr_interrupts.py
pypdfocr/pypdfocr_multiprocessing.py
pypdfocr/pypdfocr_pdf.py
pypdfocr/pypdfocr_pdffiler.py
pypdfocr/pypdfocr_preprocess.py
pypdfocr/pypdfocr_tesseract.py
pypdfocr/pypdfocr_util.py
pypdfocr/pypdfocr_watcher.py
pypdfocr/version.py
pypdfocr.egg-info/PKG-INFO
pypdfocr.egg-info/SOURCES.txt
pypdfocr.egg-info/dependency_links.txt
pypdfocr.egg-info/entry_points.txt
pypdfocr.egg-info/requires.txt
pypdfocr.egg-info/top_level.txt
pypdfocr.egg-info/zip-safe
test/test_evernote.py
test/test_gs.py
test/test_option_parsing.py
test/test_pdf_filer.py
test/test_pypdfocr.py
test/test_tesseract.py
test/test_watcher.py