Metadata-Version: 1.0
Name: pypdfocr
Version: 0.9.1
Summary: Converts a scanned PDF into an OCR'ed pdf using Tesseract-OCR and Ghostscript
Home-page: UNKNOWN
Author: Virantha N. Ekanayake
Author-email: virantha@gmail.com
License: ASL 2.0
Platform: UNKNOWN
